hdrezka/__init__.py
hdrezka/_bs4.py
hdrezka/_deobfuscation.py
hdrezka/api/__init__.py
hdrezka/api/ajax.py
hdrezka/api/http.py
hdrezka/api/search.py
hdrezka/api/types.py
hdrezka/errors.py
hdrezka/post/__init__.py
hdrezka/post/_utils/__init__.py
hdrezka/post/_utils/parser.py
hdrezka/post/info/__init__.py
hdrezka/post/info/fields.py
hdrezka/post/info/franchises.py
hdrezka/post/info/person.py
hdrezka/post/inline.py
hdrezka/post/page.py
hdrezka/post/post.py
hdrezka/post/urls/__init__.py
hdrezka/post/urls/kind/__init__.py
hdrezka/post/urls/kind/quality.py
hdrezka/post/urls/kind/subtitle.py
hdrezka/post/urls/kind/video.py
hdrezka/post/urls/urls.py
hdrezka/stream/__init__.py
hdrezka/stream/_cache.py
hdrezka/stream/player.py
hdrezka/translators.py
hdrezka/url.py
hdrezka-4.0.3.dist-info/LICENSE
hdrezka-4.0.3.dist-info/METADATA
hdrezka-4.0.3.dist-info/WHEEL
hdrezka-4.0.3.dist-info/RECORD
