Metadata-Version: 2.3
Name: hdrezka
Version: 4.0.3
Summary: HDRezka Python API
License: MIT License
Keywords: HDRezka,watch online,api,stream,m3u8,hls
Author: Nikita Denissov
Author-email: nikdissv@proton.me
Requires-Python: >=3.10
Classifier: Development Status :: 5 - Production/Stable
Classifier: Environment :: Console
Classifier: Intended Audience :: End Users/Desktop
Classifier: Intended Audience :: Information Technology
Classifier: Intended Audience :: Other Audience
Classifier: Intended Audience :: Telecommunications Industry
Classifier: License :: OSI Approved
Classifier: License :: OSI Approved :: MIT License
Classifier: Natural Language :: English
Classifier: Operating System :: OS Independent
Classifier: Programming Language :: Python :: 3
Classifier: Programming Language :: Python :: 3.10
Classifier: Programming Language :: Python :: 3.11
Classifier: Programming Language :: Python :: 3.12
Classifier: Programming Language :: Python :: 3.13
Classifier: Programming Language :: Python :: 3.14
Classifier: Topic :: Internet
Classifier: Topic :: Internet :: WWW/HTTP
Classifier: Topic :: Internet :: WWW/HTTP :: Dynamic Content
Classifier: Topic :: Multimedia :: Video
Provides-Extra: socks
Requires-Dist: beautifulsoup4 (>=4.13.4,<5.0.0)
Requires-Dist: httpx (>=0.28.1,<0.29.0)
Requires-Dist: httpx[socks] (>=0.28.1,<0.29.0) ; extra == "socks"
Requires-Dist: lxml (>=6.0.0,<7.0.0) ; python_version < "3.14"
Project-URL: Bug Tracker, https://github.com/NIKDISSV-Forever/HDRezka/issues
Project-URL: Documentation, https://nikdissv-forever.github.io/HDRezka/hdrezka
Project-URL: Homepage, https://github.com/NIKDISSV-Forever/HDRezka
Project-URL: Repository, https://github.com/NIKDISSV-Forever/HDRezka
